sort_nodes.py
cpac_indices-0.1.1.dist-info/licenses/COPYING
cpac_indices-0.1.1.dist-info/licenses/COPYING.LESSER
cpac_indices-0.1.1.dist-info/METADATA
cpac_indices-0.1.1.dist-info/WHEEL
cpac_indices-0.1.1.dist-info/entry_points.txt
cpac_indices-0.1.1.dist-info/top_level.txt
cpac_indices-0.1.1.dist-info/RECORD
