Metadata-Version: 2.4
Name: cpac_indices
Version: 0.1.1
Summary: Sort C-PAC working directory subdirectories by index.
Author-email: Child Mind Institute C-PAC Team <CMI_CPAC@childmind.org>, Jon Cluce <jon.clucas@childmind.org>
License: MIT
Keywords: C-PAC,indices,sorting
Classifier: Programming Language :: Python :: 3.10
Classifier: Programming Language :: Python :: 3.11
Classifier: Programming Language :: Python :: 3.12
Classifier: License :: OSI Approved :: GNU Lesser General Public License v3 (LGPLv3)
Classifier: Operating System :: POSIX :: Linux
Classifier: Operating System :: MacOS
Requires-Python: >=3.10
License-File: COPYING
License-File: COPYING.LESSER
Dynamic: license-file
